simpledmx/__init__.py
simpledmx-0.0.1.dist-info/LICENSE
simpledmx-0.0.1.dist-info/METADATA
simpledmx-0.0.1.dist-info/WHEEL
simpledmx-0.0.1.dist-info/top_level.txt
simpledmx-0.0.1.dist-info/RECORD
