Metadata-Version: 2.1
Name: simpledmx
Version: 0.0.1
Summary: A minimalistic user experience with SDMX that fetches all data from sources
Home-page: https://github.com/dkgaraujo/simpledmx
Author: Douglas K. G. de Araujo
Author-email: dkg.araujo@gmail.com
License: Apache License 2.0
Project-URL: Bug Tracker, https://github.com/dkgaraujo/simpledmx/issues
Platform: UNKNOWN
Classifier: Programming Language :: Python :: 3
Classifier: License :: OSI Approved :: Apache Software License
Classifier: Operating System :: OS Independent
Requires-Python: >=3.10.2
License-File: LICENSE
Requires-Dist: pandas (>=1.3.5)
Requires-Dist: pandasdmx (>=1.7.0)
Requires-Dist: requests-cache (>=0.9.1)
Requires-Dist: scikeras (>=0.4.1)
Requires-Dist: scikit-learn (>=1.0.2)
Requires-Dist: tqdm (>=4.62.3)
